app.py
pex_demo_stepanmatula-1.0.7.dist-info/licenses/LICENSE
pex_demo_stepanmatula-1.0.7.dist-info/METADATA
pex_demo_stepanmatula-1.0.7.dist-info/WHEEL
pex_demo_stepanmatula-1.0.7.dist-info/entry_points.txt
pex_demo_stepanmatula-1.0.7.dist-info/top_level.txt
pex_demo_stepanmatula-1.0.7.dist-info/RECORD
